README.md
setup.py
src/rdpc/__init__.py
src/rdpc/hello.py
src/rdpc.egg-info/PKG-INFO
src/rdpc.egg-info/SOURCES.txt
src/rdpc.egg-info/dependency_links.txt
src/rdpc.egg-info/top_level.txt