Metadata-Version: 2.1
Name: rdpc
Version: 0.0.0
Summary: Data Producer and consumer Library for Kafka.
Home-page: UNKNOWN
Author: Yulong
Author-email: yulong.wang@rakuten.com
License: UNKNOWN
Platform: UNKNOWN
